fh_bootstrap/__init__.py
fh_bootstrap/assets/bs-toc.js
fh_bootstrap/assets/fh-bootstrap.css
fh_bootstrap/assets/hl-styles.css
fh_bootstrap-0.0.3.dist-info/METADATA
fh_bootstrap-0.0.3.dist-info/WHEEL
fh_bootstrap-0.0.3.dist-info/top_level.txt
fh_bootstrap-0.0.3.dist-info/RECORD
